sec_gemini_byot/__init__.py
sec_gemini_byot/byot.py
sec_gemini_byot/byot_api.proto
sec_gemini_byot/cli.py
sec_gemini_byot/default_mcp.py
sec_gemini_byot-0.1.3.dist-info/METADATA
sec_gemini_byot-0.1.3.dist-info/WHEEL
sec_gemini_byot-0.1.3.dist-info/entry_points.txt
sec_gemini_byot-0.1.3.dist-info/RECORD
