Metadata-Version: 2.4
Name: sec-gemini-byot
Version: 0.1.3
Summary: Bring-Your-Own-Tool Client for Sec-Gemini
Requires-Python: >=3.13
Requires-Dist: fastmcp==3.0.0b1
Requires-Dist: grpcio-tools>=1.76.0
Requires-Dist: grpcio>=1.76.0
Requires-Dist: httpx>=0.28.1
Requires-Dist: pydantic>=2.12.5
Requires-Dist: rich>=14.2.0
Requires-Dist: tenacity>=9.1.2
